{"custom":{"text":"«Дүйсэн үдэр» - благодетельные поступки и греховные деяния, совершённые в этот день, приумножатся в сто раз."},"haircut":{"positive":true,"text":"к удлинению жизни."},"travel":{"positive":true,"text":"к находке, все задуманное исполнится. "},"info":"<p><strong>Благоприятный день&nbsp;</strong>для людей, родившихся в год Коровы, Тигра и Кролика; в этот день задуманные дела и вопросы будут решаться легко; писать научные труды, проводить обряд «даллга абаха», «жабтуй», надевать новую одежду, шить и кроить одежду, следить за своим распорядком дня, начинать задуманное дело, а также для жёсткого решения некоторых вопросов.</p><p><strong>Неблагоприятный день</strong>&nbsp;для людей, родившихся в год Мыши и Свиньи; покупать и продавать вещи, менять место жительства и работы, приводить невестку, отдавать дочь в невесты, проводить похороны и поминки.<br></p><p><br></p>"}